gait_modulation/__init__.py
gait_modulation/viz.py
gait_modulation/configs/base_model_config.yaml
gait_modulation/configs/classification_lstm_config.yaml
gait_modulation/configs/data_preprocessing.yaml
gait_modulation/configs/linearRegression_config.yaml
gait_modulation/configs/logistic_regression_config.yaml
gait_modulation/configs/regression_lstm_config.yaml
gait_modulation/configs/written/lfp_metadata_config.yaml
gait_modulation/models/base_model.py
gait_modulation/models/classification_models.py
gait_modulation/models/feature_extraction.py
gait_modulation/models/lstm_classification_model.py
gait_modulation/models/lstm_models.py
gait_modulation/models/regression_models.py
gait_modulation/tests/__init__.py
gait_modulation/tests/test_data_processor.py
gait_modulation/tests/test_feature_extractor.py
gait_modulation/tests/test_file_reader.py
gait_modulation/tests/test_model.py
gait_modulation/utils/_file_reader.py
gait_modulation/utils/data_processor.py
gait_modulation/utils/feature_extractor.py
gait_modulation/utils/file_reader.py
gait_modulation/utils/utils.py
gait_modulation-0.1.dist-info/licenses/LICENSE
gait_modulation-0.1.dist-info/WHEEL
gait_modulation-0.1.dist-info/METADATA
gait_modulation-0.1.dist-info/RECORD
